README.rst
edutest.py
edutest_locale_et.py
setup.py
edutest.egg-info/PKG-INFO
edutest.egg-info/SOURCES.txt
edutest.egg-info/dependency_links.txt
edutest.egg-info/top_level.txt