Metadata-Version: 1.1
Name: edutest
Version: 0.3
Summary: Utility library for writing tests in the context of teaching programming
Home-page: https://bitbucket.org/plas/edutest
Author: UNKNOWN
Author-email: UNKNOWN
License: MIT
Keywords: testing
Platform: UNKNOWN
Classifier: Development Status :: 4 - Beta
Classifier: Intended Audience :: Developers
Classifier: Intended Audience :: Education
Classifier: License :: Freeware
Classifier: License :: OSI Approved :: MIT License
Classifier: Natural Language :: English
Classifier: Programming Language :: Python
Classifier: Programming Language :: Python :: 3
Classifier: Topic :: Education
Classifier: Topic :: Software Development
Classifier: Topic :: Software Development :: Testing
